[
  {
    "id": "f2b71e86f792821b",
    "keyword": "외국인 관광객",
    "title": "외국인 일상과 여행을 잇는 로컬 가이드, 코리안나우 매거진 창간 - 투데이안",
    "url": "https://news.google.com/rss/articles/CBMiXkFVX3lxTFBxNDdDeGZianFhbTZ4Q0tQWmt6dEZSbTRybTA2LWI1WE1FMHVnR2hVdUhIRE5FSkx4VUl3RFFpSWdOc1k4Y2hETWhodWgzNmdjZVVUdWRSYnRJdktqTkE",
    "source": "투데이안",
    "publishedAt": "2026-02-03T01:12:00+00:00",
    "date": "2026-02-03",
    "snippet": "외국인 일상과 여행을 잇는 로컬 가이드, 코리안나우 매거진 창간&nbsp;&nbsp;투데이안",
    "collectedAt": "2026-02-03T01:29:27.333499+00:00"
  },
  {
    "id": "b21dd12b9e65a805",
    "keyword": "외국인 관광객",
    "title": "롯데백화점 본점, 외국인 고객 매출 비중 25% 기록 - 로이슈",
    "url": "https://news.google.com/rss/articles/CBMiekFVX3lxTE40TVRDNlhLMzhGZkNiNDhwbUtKRkVxUHVXNy10ZVNHUGlHUU44WmtkbEdFcnRRYXVYbUZUajBiTUN5YWVEQkVQdUM5S3FGd2Jib3d4QUFPeDNJZ0p4RXdHc0YxeU1QNFpxbnItTURiV2ZSM2QzTjZGSmpR",
    "source": "로이슈",
    "publishedAt": "2026-02-03T00:56:21+00:00",
    "date": "2026-02-03",
    "snippet": "롯데백화점 본점, 외국인 고객 매출 비중 25% 기록&nbsp;&nbsp;로이슈",
    "collectedAt": "2026-02-03T01:29:27.334398+00:00"
  },
  {
    "id": "d8fa137319da87d8",
    "keyword": "외국인 관광객",
    "title": "롯데百, '이것'으로 외국인 관광객 발길 이끈다 - 네이트",
    "url": "https://news.google.com/rss/articles/CBMiU0FVX3lxTE9Rb3hKdDJJdGIzNk5HcUhNRlpfX2s3YzFwczNWaHh5VUF3SnQ5SFRCMnpLZmJLTzV1RkZTOW9xb1FNa0xkUlNBelRxcWxZVUNzM2I0",
    "source": "네이트",
    "publishedAt": "2026-02-03T00:42:00+00:00",
    "date": "2026-02-03",
    "snippet": "롯데百, '이것'으로 외국인 관광객 발길 이끈다&nbsp;&nbsp;네이트",
    "collectedAt": "2026-02-03T01:29:27.332845+00:00"
  },
  {
    "id": "d91df9aa3d21ccdb",
    "keyword": "외국인 관광객",
    "title": "롯데百, `이것`으로 외국인 관광객 발길 이끈다 - 디지털데일리",
    "url": "https://news.google.com/rss/articles/CBMiZEFVX3lxTFAwZ1hkU2NOLUV6LW1VelllaG1GVWMzaWxuaW1kY1JvZ2tRQ1ZBb0Q1Uk1tRU9WWWFBSDNHR3ZHQ0NBeHV6amIwWGxKRjVZd3hmNjRIcHBCOXpZbjF3NVBVY0s3eDA",
    "source": "디지털데일리",
    "publishedAt": "2026-02-03T00:41:16+00:00",
    "date": "2026-02-03",
    "snippet": "롯데百, `이것`으로 외국인 관광객 발길 이끈다&nbsp;&nbsp;디지털데일리",
    "collectedAt": "2026-02-03T01:29:27.333258+00:00"
  },
  {
    "id": "69ee919326e35453",
    "keyword": "외국인 관광객",
    "title": "‘한국인처럼’ 살아보길 원한다는 방한 외국인 관광객이 주로 찾는 곳 - v.daum.net",
    "url": "https://news.google.com/rss/articles/CBMiT0FVX3lxTE5YU0hJZWpuX2VpVE5MbndLRXdRMEdlMHQ0MnI1VWZHdGh0MHAteEtETzJmdmFlR1BOUjBrN0x1d3pqcXBhYWE0MzF2LXA4czg",
    "source": "v.daum.net",
    "publishedAt": "2026-02-03T00:06:00+00:00",
    "date": "2026-02-03",
    "snippet": "‘한국인처럼’ 살아보길 원한다는 방한 외국인 관광객이 주로 찾는 곳&nbsp;&nbsp;v.daum.net",
    "collectedAt": "2026-02-03T01:29:27.332535+00:00"
  },
  {
    "id": "6e8f52cd65bfa1ed",
    "keyword": "외국인 관광객",
    "title": "'한국인처럼' 살아보길 원한다는 방한 외국인 관광객이 주로 찾는 곳 - 네이트",
    "url": "https://news.google.com/rss/articles/CBMiU0FVX3lxTE0tSnd5aVdfZ3E3RjdPUXMyNDg5VWM5WnNrSHVyLTFPMFVvNE9lWTllY1N4NGwtUFhyMXloOXZWTjZIcUhMc2kyYlhxQWl4Z1g3NlE4",
    "source": "네이트",
    "publishedAt": "2026-02-03T00:06:00+00:00",
    "date": "2026-02-03",
    "snippet": "'한국인처럼' 살아보길 원한다는 방한 외국인 관광객이 주로 찾는 곳&nbsp;&nbsp;네이트",
    "collectedAt": "2026-02-03T01:29:27.333620+00:00"
  }
]